more.cerberus-0.4-nspkg.pth
more/cerberus/__init__.py
more/cerberus/app.py
more/cerberus/error.py
more/cerberus/loader.py
more/cerberus/validator.py
more/cerberus/tests/__init__.py
more/cerberus/tests/test_cerberus.py
more/cerberus/tests/test_error_handling.py
more/cerberus/tests/test_translation.py
more/cerberus/tests/test_validator.py
more.cerberus-0.4.dist-info/LICENSE.txt
more.cerberus-0.4.dist-info/METADATA
more.cerberus-0.4.dist-info/WHEEL
more.cerberus-0.4.dist-info/namespace_packages.txt
more.cerberus-0.4.dist-info/top_level.txt
more.cerberus-0.4.dist-info/RECORD
