Metadata-Version: 2.1
Name: more.cerberus
Version: 0.4
Summary: Cerberus validation support for Morepath
Home-page: https://github.com/morepath/more.cerberus
Author: Henri Hulski
Author-email: henri.hulski@gazeta.pl
License: BSD
Keywords: morepath validation
Classifier: Intended Audience :: Developers
Classifier: License :: OSI Approved :: BSD License
Classifier: Programming Language :: Python :: 3.8
Classifier: Programming Language :: Python :: 3.9
Classifier: Programming Language :: Python :: 3.10
Classifier: Programming Language :: Python :: 3.11
Classifier: Programming Language :: Python :: 3.12
Classifier: Programming Language :: Python :: Implementation :: PyPy
License-File: LICENSE.txt
Requires-Dist: cerberus <2.0.0,>=1.3.2
Requires-Dist: morepath >=0.19
Provides-Extra: coverage
Requires-Dist: pytest-cov ; extra == 'coverage'
Provides-Extra: pep8
Requires-Dist: black ; extra == 'pep8'
Requires-Dist: flake8 ; extra == 'pep8'
Provides-Extra: test
Requires-Dist: pytest-remove-stale-bytecode ; extra == 'test'
Requires-Dist: pytest >=2.9.1 ; extra == 'test'
Requires-Dist: webtest ; extra == 'test'
